napari_apple/__init__.py
napari_apple/_reader.py
napari_apple/_sample_data.py
napari_apple/_widget.py
napari_apple/_writer.py
napari_apple/napari.yaml
napari_apple/path.py
napari_apple/result.txt
napari_apple/_tests/__init__.py
napari_apple/_tests/test_reader.py
napari_apple/_tests/test_sample_data.py
napari_apple/_tests/test_widget.py
napari_apple/_tests/test_writer.py
napari_apple/main_folder/obj.data
napari_apple/main_folder/obj.names
napari_apple/main_folder/yolov4-tiny-train.cfg
napari_apple/weight-darknet/notice.txt
napari_apple/weight-darknet/yolov4-tiny-960.h5
napari_apple-0.0.8.dist-info/LICENSE
napari_apple-0.0.8.dist-info/METADATA
napari_apple-0.0.8.dist-info/WHEEL
napari_apple-0.0.8.dist-info/entry_points.txt
napari_apple-0.0.8.dist-info/top_level.txt
napari_apple-0.0.8.dist-info/RECORD
